azure/mgmt/graphservices/__init__.py
azure/mgmt/graphservices/_configuration.py
azure/mgmt/graphservices/_graph_services_mgmt_client.py
azure/mgmt/graphservices/_patch.py
azure/mgmt/graphservices/_serialization.py
azure/mgmt/graphservices/_vendor.py
azure/mgmt/graphservices/_version.py
azure/mgmt/graphservices/py.typed
azure/mgmt/graphservices/aio/__init__.py
azure/mgmt/graphservices/aio/_configuration.py
azure/mgmt/graphservices/aio/_graph_services_mgmt_client.py
azure/mgmt/graphservices/aio/_patch.py
azure/mgmt/graphservices/aio/operations/__init__.py
azure/mgmt/graphservices/aio/operations/_accounts_operations.py
azure/mgmt/graphservices/aio/operations/_operations.py
azure/mgmt/graphservices/aio/operations/_patch.py
azure/mgmt/graphservices/models/__init__.py
azure/mgmt/graphservices/models/_graph_services_mgmt_client_enums.py
azure/mgmt/graphservices/models/_models_py3.py
azure/mgmt/graphservices/models/_patch.py
azure/mgmt/graphservices/operations/__init__.py
azure/mgmt/graphservices/operations/_accounts_operations.py
azure/mgmt/graphservices/operations/_operations.py
azure/mgmt/graphservices/operations/_patch.py
azure_mgmt_graphservices-1.0.0.dist-info/LICENSE
azure_mgmt_graphservices-1.0.0.dist-info/METADATA
azure_mgmt_graphservices-1.0.0.dist-info/WHEEL
azure_mgmt_graphservices-1.0.0.dist-info/top_level.txt
azure_mgmt_graphservices-1.0.0.dist-info/RECORD
